ZetcodeJavaJiaochengChuyi/README.md
ZetcodeJavaJiaochengChuyi/__init__.py
ZetcodeJavaJiaochengChuyi/__main__.py
ZetcodeJavaJiaochengChuyi/file.epub
ZetcodeJavaJiaochengChuyi/index.html
ZetcodeJavaJiaochengChuyi/css/__init__.py
ZetcodeJavaJiaochengChuyi/css/annotations.css
ZetcodeJavaJiaochengChuyi/css/main.css
ZetcodeJavaJiaochengChuyi/css/normalize.css
ZetcodeJavaJiaochengChuyi/css/popup.css
ZetcodeJavaJiaochengChuyi/font/__init__.py
ZetcodeJavaJiaochengChuyi/font/fontello.eot
ZetcodeJavaJiaochengChuyi/font/fontello.svg
ZetcodeJavaJiaochengChuyi/font/fontello.ttf
ZetcodeJavaJiaochengChuyi/font/fontello.woff
ZetcodeJavaJiaochengChuyi/img/__init__.py
ZetcodeJavaJiaochengChuyi/img/annotator-glyph-sprite.png
ZetcodeJavaJiaochengChuyi/img/annotator-icon-sprite.png
ZetcodeJavaJiaochengChuyi/img/apple-touch-icon.png
ZetcodeJavaJiaochengChuyi/img/cancelfullscreen.png
ZetcodeJavaJiaochengChuyi/img/close.png
ZetcodeJavaJiaochengChuyi/img/fullscreen.png
ZetcodeJavaJiaochengChuyi/img/loader.gif
ZetcodeJavaJiaochengChuyi/img/menu-icon.png
ZetcodeJavaJiaochengChuyi/img/save.png
ZetcodeJavaJiaochengChuyi/img/saved.png
ZetcodeJavaJiaochengChuyi/img/settings-s.png
ZetcodeJavaJiaochengChuyi/img/settings.png
ZetcodeJavaJiaochengChuyi/img/star.png
ZetcodeJavaJiaochengChuyi/js/__init__.py
ZetcodeJavaJiaochengChuyi/js/epub.js
ZetcodeJavaJiaochengChuyi/js/epub.min.js
ZetcodeJavaJiaochengChuyi/js/epub.min.map
ZetcodeJavaJiaochengChuyi/js/hooks.min.js
ZetcodeJavaJiaochengChuyi/js/hooks.min.map
ZetcodeJavaJiaochengChuyi/js/reader.js
ZetcodeJavaJiaochengChuyi/js/reader.js.map
ZetcodeJavaJiaochengChuyi/js/reader.min.js
ZetcodeJavaJiaochengChuyi/js/reader.min.map
ZetcodeJavaJiaochengChuyi/js/hooks/__init__.py
ZetcodeJavaJiaochengChuyi/js/hooks/extensions/__init__.py
ZetcodeJavaJiaochengChuyi/js/hooks/extensions/highlight.js
ZetcodeJavaJiaochengChuyi/js/libs/__init__.py
ZetcodeJavaJiaochengChuyi/js/libs/jquery.min.js
ZetcodeJavaJiaochengChuyi/js/libs/localforage.min.js
zetcode_java_jiaocheng_chuyi-2024.3.5.0.dist-info/METADATA
zetcode_java_jiaocheng_chuyi-2024.3.5.0.dist-info/WHEEL
zetcode_java_jiaocheng_chuyi-2024.3.5.0.dist-info/entry_points.txt
zetcode_java_jiaocheng_chuyi-2024.3.5.0.dist-info/top_level.txt
zetcode_java_jiaocheng_chuyi-2024.3.5.0.dist-info/RECORD
